README.md
setup.py
DatastoreLogger/__init__.py
Flask_DatastoreLogger.egg-info/PKG-INFO
Flask_DatastoreLogger.egg-info/SOURCES.txt
Flask_DatastoreLogger.egg-info/dependency_links.txt
Flask_DatastoreLogger.egg-info/requires.txt
Flask_DatastoreLogger.egg-info/top_level.txt