Metadata-Version: 2.1
Name: Flask-DatastoreLogger
Version: 0.0.3
Summary: A logging interface for Google Cloud Datastore
Home-page: https://github.com/MobiusWorksLLC/Flask-DatastoreLogger
Author: Tyson Holub
Author-email: tholub@mobiusworks.com
License: MIT
Platform: UNKNOWN
